[{"inputName":"123123123","inputAddress":"123123213","inputNPA":"12321321","inputCity":"3213213","inputNameAnnonce":"12321312","inputDescription":"12312312","inputAvailableDate":"2021-01-20","inputPictures":"download.jpg","inputPrice":"1232313","Email":"sgi@gmail.com","active":true,"ID":0},{"inputName":"123123123","inputAddress":"123123213","inputNPA":"12321321","inputCity":"3213213","inputNameAnnonce":"123213","inputDescription":"123123","inputAvailableDate":"2021-04-01","inputPictures":"download.jpg","inputPrice":"333333","Email":"sgi@gmail.com","active":true,"ID":1}]